{
  "AUGSBURG": [
    ["Fuggerei Augsburg", "https://www.fuggerei.de"],
    ["Zoo Augsburg", "https://www.zoo-augsburg.de"],
    ["Bunter Kreis", "https://www.bunter-kreis.de"],
    ["Augsburger Tafel", "https://augsburger-tafel.de"],
    ["Tierheim Augsburg", "https://www.tierheim-augsburg.de"],
    ["Hospiz-Gruppe Augsburg", "https://www.hospiz-augsburg.de"],
    ["SKM Augsburg", "https://www.skm-augsburg.de"],
    ["Freiwilligen-Zentrum Augsburg", "https://www.freiwilligen-zentrum-augsburg.de"],
    ["Kulturküche Augsburg", "https://die-kulturkueche.de"],
    ["Lese-Inseln Augsburg", "https://www.lese-inseln.de"],
    ["Fritz-Felsenstein-Haus", "https://www.felsenstein.org"],
    ["Kinderschutzbund Augsburg", "https://www.kinderschutzbund-augsburg.de"],
    ["Kartei der Not", "https://www.kartei-der-not.de"],
    ["Tür an Tür e.V.", "https://tuerantuer.de"],
    ["Malteser Augsburg", "https://www.malteser-augsburg.de"],
    ["Johanniter Augsburg", "https://www.johanniter.de/augsburg"],
    ["BRK Augsburg", "https://www.kvaugsburg-stadt.brk.de"],
    ["St. Gregor Jugendhilfe", "https://www.st-gregor.de"],
    ["Öko-Modellregion Augsburg", "https://www.augsburg.de/umwelt-soziales/umwelt/oekomodellregion"],
    ["Stadtbücherei Augsburg", "https://www.augsburg.de/kultur/bibliotheken/stadtbuecherei"],
    ["Boxclub Augsburg Integration", "https://www.boxclub-augsburg.de"],
    ["Drahtesel Augsburg", "https://www.drahtesel-augsburg.de"],
    ["Bahnhofsmission Augsburg", "https://www.bahnhofsmission.de/index.php?id=81"],
    ["Klimacamp Augsburg", "https://www.klimacamp-augsburg.de"],
    ["Grandhotel Cosmopolis", "https://grandhotel-cosmopolis.org"],
    ["Sensemble Theater", "https://sensemble.de"],
    ["Kulturhaus Abraxas", "https://www.augsburg.de/kultur/kulturhaeuser/kulturhaus-abraxas"],
    ["Weltladen Augsburg", "https://www.weltladen-augsburg.de"],
    ["Transition Town Augsburg", "https://www.tt-augsburg.de"],
    ["Solidarische Landwirtschaft Augsburg", "https://solawi-augsburg.de"],
    ["Freunde der Puppenkiste", "https://www.puppenkiste.com"],
    ["Botanischer Garten Augsburg", "https://www.augsburg.de/freizeit/ausflugsziele/botanischer-garten"],
    ["Tierhilfe Augsburg e.V.", "https://www.tierhilfe-augsburg.de"],
["Betterplace","
https://www.betterplace.org/de/projects/73101-vierpfotiger-therapeut-fuer-senioren-mit-demenziellen-erkrankungen "],
    ["AWO Schwaben", "https://www.awo-schwaben.de"],
[ "Feuerwhrfound","https://www.betterplace.org/de/projects/28013?utm_campaign=user_share&utm_medium=ppp_sticky&utm_source=Link&utm_content=bp"],
  ],
  "BAYERN": [
    ["Sternstunden e.V.", "https://www.sternstunden.de"],
    ["LBV Bayern", "https://www.lbv.de"],
    ["Bund Naturschutz Bayern", "https://www.bund-naturschutz.de"],
    ["Tafel Bayern", "https://www.tafel-bayern.de"],
    ["Antenne Bayern hilft", "https://www.antenne-bayern-hilft.de"],
    ["Bergwacht Bayern", "https://www.bergwacht-bayern.de"],
    ["Wasserwacht Bayern", "https://www.wasserwacht-bayern.de"],
    ["Landesfeuerwehrverband Bayern", "https://www.lfv-bayern.de"],
    ["Bayerische Krebsgesellschaft", "https://www.bayerische-krebsgesellschaft.de"],
    ["Ambulantes Kinderhospiz München", "https://www.kinderhospiz-muenchen.de"],
    ["Kitzrettung Bayern", "https://www.kitzrettung-bayern.de"],
    ["Blindenbund Bayern", "https://www.bbsb.org"],
    ["Bayerisches Rotes Kreuz", "https://www.brk.de"],
    ["Bayern barrierefrei", "https://www.barrierefrei.bayern.de"]
  ],
  "DEUTSCHLAND": [
    ["Brot für die Welt", "https://www.brot-fuer-die-welt.de"],
    ["Caritas International", "https://www.caritas-international.de"],
    ["Johanniter Auslandshilfe", "https://www.johanniter.de/auslandshilfe"],
    ["Tafel Deutschland", "https://www.tafel.de"],
    ["NABU", "https://www.nabu.de"],
    ["BUND", "https://www.bund.net"],
    ["Atmosfair", "https://www.atmosfair.de"],
    ["Aktion Deutschland Hilft", "https://www.aktion-deutschland-hilft.de"],
    ["DKMS", "https://www.dkms.de"],
    ["Sanfilippo Initiative", " https://sanfilippoinitiative.org/home/"]
  ],
  "SPANIEN": [
    ["Cáritas Española", "https://www.caritas.es"],
    ["Cruz Roja Española", "https://www.cruzroja.es"],
    ["Open Arms", "https://www.openarms.es"],
    ["Fundación Juegaterapia", "https://www.juegaterapia.org"],
    ["Asociación Española Contra el Cáncer", "https://www.contraelcancer.es"]
  ],
  "BOSNIEN": [
    ["Pomozi.ba", "https://www.pomozi.ba"],
    ["Revolucija", "https://revolucija.ba"],
    ["Mozaik Foundation", "https://mozaik.ba"],
    ["Merhamet", "https://merhamet.ba"]
  ],
  "GLOBAL": [
    ["Charity: Water", "https://www.charitywater.org"],
    ["UNICEF", "https://www.unicef.org"],
    ["UNHCR", "https://www.unhcr.org"],
    ["World Food Programme", "https://www.wfp.org"],
    ["International Rescue Committee", "https://www.rescue.org"],
    ["Save the Children", "https://www.savethechildren.net"],
    ["CARE", "https://www.care.org"],
    ["Oxfam", "https://www.oxfam.org"],
    ["Habitat for Humanity", "https://www.habitat.org"],
    ["WaterAid", "https://www.wateraid.org"],
    ["Mercy Corps", "https://www.mercycorps.org"],
    ["Plant-for-the-Planet", "https://www.plant-for-the-planet.org"],
    ["The Ocean Cleanup", "https://theoceancleanup.com"],
    ["Rainforest Trust", "https://www.rainforesttrust.org"],
    ["350.org", "https://350.org"],
    ["Clean Air Task Force", "https://www.catf.us"],
    ["Project Drawdown", "https://drawdown.org"],
    ["CarbonFund", "https://carbonfund.org"],
    ["Carbon180", "https://carbon180.org"],
    ["Climeworks", "https://climeworks.com"],
    ["Eden Reforestation Projects", "https://www.edenprojects.org"],
    ["Trees for the Future", "https://trees.org"],
    ["Solar Sister", "https://solarsister.org"],
    ["Wikimedia Foundation", "https://wikimediafoundation.org"],
    ["Khan Academy", "https://www.khanacademy.org"],
    ["Mozilla Foundation", "https://foundation.mozilla.org"],
    ["Open Knowledge Foundation", "https://okfn.org"],
    ["Code.org", "https://code.org"]
  ],
  "MEDIZIN": [
    ["St. Jude Children's Research Hospital", "https://www.stjude.org"],
    ["Michael J. Fox Foundation", "https://www.michaeljfox.org"],
    ["Cancer Research Institute", "https://www.cancerresearch.org"],
    ["Global Genes", "https://globalgenes.org"],
    ["Cure SMA", "https://www.curesma.org"],
    ["Alzheimer's Research UK", "https://www.alzheimersresearchuk.org"],
    ["WHO Foundation", "https://who.foundation"]
  ],
  "UMWELT": [
    ["Rewilding Europe", "https://rewildingeurope.com"],
    ["Protect Our Winters", "https://protectourwinters.org"]
  ],
  "COMMUNITY": [
    ["Vortex Karma Vorschlag", "https://senci33-wq.github.io/Vortex-Lotto-Global-Karma-2026/"]
  ]
}
